{
  "STS2_WINE_FOX_CARD_WINE_FOX_STRIKE.title": "打击",
  "STS2_WINE_FOX_CARD_WINE_FOX_STRIKE.description": "造成 {Damage:diff()} 点伤害。",
  "STS2_WINE_FOX_CARD_WINE_FOX_DEFEND.title": "防御",
  "STS2_WINE_FOX_CARD_WINE_FOX_DEFEND.description": "获得 {Block:diff()} 点格挡。",
  "STS2_WINE_FOX_CARD_BASIC_MINE.title": "基础采掘",
  "STS2_WINE_FOX_CARD_BASIC_MINE.description": "获得 {Wood:diff()} [gold]木板[/gold] 和 {Stone:diff()} [gold]圆石[/gold]。",
  "STS2_WINE_FOX_CARD_STONE_PICKAXE.title": "石镐",
  "STS2_WINE_FOX_CARD_STONE_PICKAXE.description": "每回合开始时，获得 [blue]1[/blue] 个[gold]木板[/gold]和 [blue]1[/blue] 个[gold]圆石[/gold]。\n(1个[gold]木板[/gold],3个[gold]圆石[/gold])",
  "STS2_WINE_FOX_CARD_BASE_CRAFT.title": "基础合成",
  "STS2_WINE_FOX_CARD_BASE_CRAFT.description": "获得 {Block:diff()} 点格挡。根据拥有的[gold]木板[/gold]，[gold]圆石[/gold]，[gold]铁锭[/gold]层数，[gold]选择[/gold]获得一张卡牌并消耗对应材料。",
  "STS2_WINE_FOX_CARD_FULL_ATTACK.title": "全力倾泻",
  "STS2_WINE_FOX_CARD_FULL_ATTACK.description": "消耗所有[gold]木板[/gold]和[gold]圆石[/gold]。\n对随机一名敌人造成{Damage:diff()}点伤害。{InCombat:\n(命中{Hits:diff()}次)|}",
  "STS2_WINE_FOX_CARD_MINING_GEMS.title": "挖掘宝石",
  "STS2_WINE_FOX_CARD_MINING_GEMS.description": "获得 {Diamond:diff()} 个[gold]钻石[/gold]。",
  "STS2_WINE_FOX_CARD_PLANT_TREES.title": "种植树木",
  "STS2_WINE_FOX_CARD_PLANT_TREES.description": "获得 {Block:diff()} 点格挡。在下回合开始时获得 [blue]{Plant:diff()}[/blue] 个[gold]木板[/gold]",
  "STS2_WINE_FOX_CARD_STEAM_ENGINE.title": "蒸汽引擎",
  "STS2_WINE_FOX_CARD_STEAM_ENGINE.description": "每回合开始时获得 {Steam:diff()} [gold]应力[/gold]。",
  "STS2_WINE_FOX_CARD_STONE_SWORD.title": "石剑",
  "STS2_WINE_FOX_CARD_STONE_SWORD.description": "造成 {Damage:diff()} 点伤害。\n获得 {StrengthPower:diff()} 层[gold]力量[/gold]。\n(1个[gold]木板[/gold],2个[gold]圆石[/gold])",
  "STS2_WINE_FOX_CARD_IRON_ARMOR.title": "铁甲",
  "STS2_WINE_FOX_CARD_IRON_ARMOR.description": "获得 {Armor:diff()} 层[gold]覆甲[/gold]。\n(8个[gold]铁锭[/gold])",
  "STS2_WINE_FOX_CHOOSE_CRAFT": "选择一张要合成的卡牌",
  "STS2_WINE_FOX_CARD_MECHANICAL_DRILL.title": "动力钻头",
  "STS2_WINE_FOX_CARD_MECHANICAL_DRILL.description": "获得 {Iron:diff()} 个[gold]铁锭[/gold]。如果消耗了[gold]应力[/gold]，返还 2 点能量。",
  "STS2_WINE_FOX_CARD_WOODEN_SWORD.title": "木剑",
  "STS2_WINE_FOX_CARD_WOODEN_SWORD.description": "造成 {Damage:diff()} 点伤害。\n获得 {Vigorous:diff()} 层[gold]活力[/gold]。\n(3个[gold]木板[/gold])",
  "STS2_WINE_FOX_CARD_IRON_PICKAXE.title": "铁镐",
  "STS2_WINE_FOX_CARD_IRON_PICKAXE.description": "接下来 {Times:diff()} 次获得资源时，额外获得 [blue]2[/blue] 个[gold]铁锭[/gold]。\n(1个[gold]木板[/gold],3个[gold]铁锭[/gold])",
  "STS2_WINE_FOX_CARD_DIAMOND_SWORD.title": "钻石剑",
  "STS2_WINE_FOX_CARD_DIAMOND_SWORD.description": "造成 {Damage:diff()} 点伤害。\n每回合前 {Echoes:diff()} 张[gold]攻击[/gold]牌额外打出一次。\n(1个[gold]木板[/gold],2个[gold]钻石[/gold])",
  "STS2_WINE_FOX_CARD_MECHANICAL_SAW.title": "动力锯",
  "STS2_WINE_FOX_CARD_MECHANICAL_SAW.description": "消耗 1 应力，对所有敌人造成 {Damage:diff()} 点伤害。",
  "STS2_WINE_FOX_CARD_IRON_SWORD.title": "铁剑",
  "STS2_WINE_FOX_CARD_IRON_SWORD.description": "造成 {Damage:diff()} 点伤害。\n下一张[gold]攻击[/gold]牌额外打出一次。\n(1个[gold]木板[/gold],2个[gold]铁锭[/gold])",
  "STS2_WINE_FOX_CARD_ALTER_PATH.title": "另辟蹊径",
  "STS2_WINE_FOX_CARD_ALTER_PATH.description": "消耗 2 木板，获得 {Block:diff()} 点格挡，抽 3 张牌。",
  "STS2_WINE_FOX_CARD_STONE_ARMOR.title": "砖石甲",
  "STS2_WINE_FOX_CARD_STONE_ARMOR.description": "获得 7 层[gold]覆甲[/gold]，回合开始时失去 1 点敏捷。\n(8个[gold]圆石[/gold])",
  "STS2_WINE_FOX_CARD_POWER_UP.title": "换挡，加速，起飞",
  "STS2_WINE_FOX_CARD_POWER_UP.description": "获得 {Stress:diff()} 层应力。抽 {Cards:diff()} 张牌。",
  "STS2_WINE_FOX_CARD_IRON_ZOMBIE.title": "\"白色僵尸\"",
  "STS2_WINE_FOX_CARD_IRON_ZOMBIE.description": "造成 {Damage:diff()} 点伤害，获得 [blue]{Iron:diff()}[/blue] 个铁锭。",
  "STS2_WINE_FOX_CARD_CRUSHING_WHEEL.title": "粉碎轮组",
  "STS2_WINE_FOX_CARD_CRUSHING_WHEEL.description": "对所有敌人造成 {Damage:diff()} 点伤害。每在本回合消耗过一次[gold]材料[/gold]，这张卡的费用就-1。",
  "STS2_WINE_FOX_CARD_ENMERGENCY_REPAIR.title": "紧急修复",
  "STS2_WINE_FOX_CARD_ENMERGENCY_REPAIR.description": "造成 {Damage:diff()} 伤害，获得 {Block:diff()} 格挡，在下个回合开始时获得 2 [gold]应力[/gold]。",
  "STS2_WINE_FOX_CARD_LIGHT_ASSAULT.title": "轻装突击",
  "STS2_WINE_FOX_CARD_LIGHT_ASSAULT.description": "造成 {Damage:diff()} 点伤害。你每有 1 份[gold]材料[/gold]，这张牌的伤害就降低 1 点。"
  
  
  
  
}